{
  "ticker": "AMZN",
  "as_of": "2026-02-03",
  "current_price": 238.62,
  "stats": {
    "52w_high": 244.22,
    "52w_low": 184.42,
    "vs_52w_high_pct": -0.022930144951273417,
    "cagr_5yr": 0.09214183621671612,
    "return_1mo": -0.0028416213957375962,
    "return_1yr": 0.2541784925890887,
    "return_5yr": 0.5424294135898231,
    "volatility_cv": 0.2587957901118315,
    "avg_price_5yr": 166.3004083333333,
    "vs_5yr_avg_pct": 0.4348732056129951
  },
  "history_recent": [
    {
      "date": "2025-03-31",
      "close": 190.26,
      "volume": 966335482.0
    },
    {
      "date": "2025-04-30",
      "close": 184.42,
      "volume": 1313093455.0
    },
    {
      "date": "2025-05-30",
      "close": 205.01,
      "volume": 937367052.0
    },
    {
      "date": "2025-06-30",
      "close": 219.39,
      "volume": 870802903.0
    },
    {
      "date": "2025-07-31",
      "close": 234.11,
      "volume": 856016326.0
    },
    {
      "date": "2025-08-29",
      "close": 229.0,
      "volume": 877727758.0
    },
    {
      "date": "2025-09-30",
      "close": 219.57,
      "volume": 962232666.0
    },
    {
      "date": "2025-10-31",
      "close": 244.22,
      "volume": 1196876750.0
    },
    {
      "date": "2025-11-28",
      "close": 233.22,
      "volume": 900896651.0
    },
    {
      "date": "2025-12-31",
      "close": 230.82,
      "volume": 787493376.0
    },
    {
      "date": "2026-01-30",
      "close": 239.3,
      "volume": 841068727.0
    },
    {
      "date": "2026-02-03",
      "close": 238.62,
      "volume": 88024675.0
    }
  ],
  "history_annual": [
    {
      "year": "2021",
      "date": "2021-12-31",
      "close": 166.717
    },
    {
      "year": "2022",
      "date": "2022-12-30",
      "close": 84.0
    },
    {
      "year": "2023",
      "date": "2023-12-29",
      "close": 151.94
    },
    {
      "year": "2024",
      "date": "2024-12-31",
      "close": 219.39
    },
    {
      "year": "2025",
      "date": "2025-12-31",
      "close": 230.82
    },
    {
      "year": "2026",
      "date": "2026-02-03",
      "close": 238.62
    }
  ]
}